opentelemetry/instrumentation/anthropic/__init__.py
opentelemetry_instrumentation_anthropic_test-0.1.0.dist-info/METADATA
opentelemetry_instrumentation_anthropic_test-0.1.0.dist-info/WHEEL
opentelemetry_instrumentation_anthropic_test-0.1.0.dist-info/RECORD
