Metadata-Version: 2.1
Name: opentelemetry-instrumentation-anthropic-test
Version: 0.1.0
Summary: OpenTelemetry Anthropic instrumentation
License: Apache-2.0
Author: Gal Kleinman
Author-email: gal@traceloop.com
Requires-Python: >=3.8.1,<3.12
Classifier: License :: OSI Approved :: Apache Software License
Classifier: Programming Language :: Python :: 3
Classifier: Programming Language :: Python :: 3.9
Classifier: Programming Language :: Python :: 3.10
Classifier: Programming Language :: Python :: 3.11
Requires-Dist: opentelemetry-api (>=1.20.0,<2.0.0)
Requires-Dist: opentelemetry-instrumentation (>=0.40b0,<0.41)
Requires-Dist: opentelemetry-semantic-conventions-llm (>=0.0.1,<0.0.2)
